{
    "author": "andreas",
    "author_url": "https://manessinger.com/",
    "date": "2007-10-15 22:06:00",
    "indent_level": 0,
    "content": "Michael,<br/><br/>You're absolutely right, this image is about light and shadow, everything else is for balance 🙂<br/><br/>Regarding style, well, as I have said, I have a problem with the word. Most of the time it is used in a very rigid sense. Mr A has style B. And the mechanisms of market really do their best to amplify this. I mean, when people can buy a Salvador Dalí with crutches or one without, which one will they take?<br/><br/>But, of course, thinking about style the way you do makes sense. I really like the notion of choices and preferences. It's not always the same choices that we make, but more often than not, and our preferences may change eventually, but they tend to stay for a long time.<br/><br/>Hmm ... it's always a pleasure to converse with intelligent people, and enlightening too.<br/><br/>Thanks"
}
