{
    "id": "6228",
    "author": "Gina",
    "author_url": "http://fyneimages.blogspot.com/",
    "date": "2010-03-10 06:38:00",
    "indent_level": 0,
    "content": "i love graffitti when i find it /capture it but i must admit i would not like it on my own property ... tis a fine line ...   i hope you feel better soooooon ... at least with the onset of spring that might help a feeling of well being ? ... \n\ni really really will one day explore the music links you provide ... i am in awe of the consistency with which you provide a song  that relates, with every post ...\n\nregards &gt;&gt;&gt; Gina\nhttp://fyneimages.blogspot.com/ \nhttp://ginaseye.blogspot.com/"
}
