{
    "author": "andreas",
    "author_url": "https://manessinger.com/",
    "date": "2015-02-10 09:31:47",
    "indent_level": 1,
    "content": "John, as I said, I'm happy with what I've got. Had I had a longer lens, I could have isolated the one swan spreading its wings and that would have been an even much better image. Why? Probably because it's rare to point a long lens with the perfect focal length and a wide aperture at exactly the right moment ... and even nail focus 🙂\n\nTechnically the same image with a longer lens is harder to get, which makes it more desireable. Take an image from space. Lots of such swans on it, right? 🙂"
}
