{
    "id": "6381",
    "author": "Esther Emma",
    "author_url": "http://www.fotoemma.blogspot.com",
    "date": "2010-03-30 10:58:25",
    "indent_level": 0,
    "content": "this square, circled square or maybe i should say piazza\nwell it doesn't matter this place in vienna reminds me of place they filmed in the motion picture 'before sunrise'. it has the same mood.\nand i love the morning light in here\nso promise-ful\ni think that's we we love spring so much\nit's full of promises\nit's something in the air \nor maybe the quality of light\ni don't know\nbut i do know i love it"
}
