{
    "id": "3026",
    "author": "April",
    "author_url": "",
    "date": "2009-05-06 22:07:00",
    "indent_level": 0,
    "content": "\"...the Image of the Day (which may also end up as the title image)\"<br /><br />I can <b>so</b> imagine that! Depending on how things develop, of course.<br /><br />And am reminded of something Joe McNally wrote in <i>The Moment it Clicks</i>: \"The two major pieces of any picture story are your opener and closer. I just got the closer.\"<br /><br />Or in your case, the opener!"
}
