{
    "id": "58302",
    "author": "Bill Birtch",
    "author_url": "http://blabirch.blogspot.com/",
    "date": "2013-05-30 16:02:15",
    "indent_level": 0,
    "content": "Great image. Love the contrast between the eroded piece and the rest of the image. Seems to me that you've captured the 'natur'al process of erosion here. Nature's effect rather than nature herself.  Then again, nature is anything but static in and of itself so maybe it's all about process.  Is the distinction meaningful? Not really."
}
