{
    "author": "andreas",
    "author_url": "https://manessinger.com/",
    "date": "2011-10-06 16:47:07",
    "indent_level": 1,
    "content": "Well, <a href=\"http://imagefiction.blogspot.com/\" rel=\"nofollow\">Ted Byrne</a> once taught me his method of making squares. Open the image in Photoshop, go to crop mode, span up a square, make it proportionally smaller (Alt-Shift-CornerDrag), and then shift the square around inside the image, if you feel like that even rotate it. You'll be surprised. It's just like looking through a viewfinder, and you'll notice that there is hardly an image without a good square in it 🙂"
}
