{
    "id": "58760",
    "author": "Markus",
    "author_url": "http://markus-spring.info",
    "date": "2013-06-17 15:19:11",
    "indent_level": 0,
    "content": "Unfortunately I do share your pessimism on that subject. As long as stupid nationalism (and even the more stupid distinction in we/good and others/evil) rules, there won't be a positive development, but an unholy mixture of pretended national and private monetarian interests tittytaining the majority while disenfranchising those that don't fit in the pattern of a still active thinking of racial/religious superiority."
}
