{
    "id": "5318",
    "author": "joan v",
    "author_url": "http://web.me.com/joanlvh/Site_/photography/photography.html",
    "date": "2010-01-02 01:45:13",
    "indent_level": 0,
    "content": "I like your first image and your lighter image with the road and trees. You mentioned that the second and third pictures were jpegs from your camera, does that mean your first was Raw, do you often switch back and forth from raw to jpeg within a short period of time?  thanks for your wonderful site, I look at it daily.   joanlvh"
}
